{
	"name": "BG_ChPoRight",
	"plugin-id": "Sprite",
	"sid": 838536170847379,
	"isGlobal": false,
	"editorNewInstanceIsReplica": true,
	"instanceVariables": [],
	"behaviorTypes": [],
	"effectTypes": [],
	"animations": {
		"items": [
			{
				"frames": [
					{
						"width": 16,
						"height": 16,
						"originX": 0,
						"originY": 0,
						"originalSource": "",
						"exportFormat": "lossless",
						"exportQuality": 0.8,
						"fileType": "image/png",
						"imageSpriteId": 9172156,
						"useCollisionPoly": true,
						"duration": 1,
						"tag": ""
					},
					{
						"width": 16,
						"height": 16,
						"originX": 0,
						"originY": 0,
						"originalSource": "",
						"exportFormat": "lossless",
						"exportQuality": 0.8,
						"fileType": "image/png",
						"imageSpriteId": 9060209,
						"useCollisionPoly": true,
						"duration": 1,
						"tag": ""
					},
					{
						"width": 16,
						"height": 16,
						"originX": 0,
						"originY": 0,
						"originalSource": "",
						"exportFormat": "lossless",
						"exportQuality": 0.8,
						"fileType": "image/png",
						"imageSpriteId": 6277002,
						"useCollisionPoly": true,
						"duration": 1,
						"tag": ""
					},
					{
						"width": 16,
						"height": 16,
						"originX": 0,
						"originY": 0,
						"originalSource": "",
						"exportFormat": "lossless",
						"exportQuality": 0.8,
						"fileType": "image/png",
						"imageSpriteId": 7551975,
						"useCollisionPoly": true,
						"duration": 1,
						"tag": ""
					}
				],
				"sid": 521942019926058,
				"name": "Top",
				"isLooping": true,
				"isPingPong": false,
				"repeatCount": 1,
				"repeatTo": 0,
				"speed": 8
			},
			{
				"frames": [
					{
						"width": 16,
						"height": 16,
						"originX": 0,
						"originY": 0,
						"originalSource": "",
						"exportFormat": "lossless",
						"exportQuality": 0.8,
						"fileType": "image/png",
						"imageSpriteId": 1075415,
						"useCollisionPoly": true,
						"duration": 1,
						"tag": ""
					},
					{
						"width": 16,
						"height": 16,
						"originX": 0,
						"originY": 0,
						"originalSource": "",
						"exportFormat": "lossless",
						"exportQuality": 0.8,
						"fileType": "image/png",
						"imageSpriteId": 240123,
						"useCollisionPoly": true,
						"duration": 1,
						"tag": ""
					},
					{
						"width": 16,
						"height": 16,
						"originX": 0,
						"originY": 0,
						"originalSource": "",
						"exportFormat": "lossless",
						"exportQuality": 0.8,
						"fileType": "image/png",
						"imageSpriteId": 7737765,
						"useCollisionPoly": true,
						"duration": 1,
						"tag": ""
					},
					{
						"width": 16,
						"height": 16,
						"originX": 0,
						"originY": 0,
						"originalSource": "",
						"exportFormat": "lossless",
						"exportQuality": 0.8,
						"fileType": "image/png",
						"imageSpriteId": 3639394,
						"useCollisionPoly": true,
						"duration": 1,
						"tag": ""
					}
				],
				"sid": 517479988602705,
				"name": "Middle",
				"isLooping": true,
				"isPingPong": false,
				"repeatCount": 1,
				"repeatTo": 0,
				"speed": 8
			},
			{
				"frames": [
					{
						"width": 16,
						"height": 16,
						"originX": 0,
						"originY": 0,
						"originalSource": "",
						"exportFormat": "lossless",
						"exportQuality": 0.8,
						"fileType": "image/png",
						"imageSpriteId": 3339869,
						"useCollisionPoly": true,
						"duration": 1,
						"tag": ""
					},
					{
						"width": 16,
						"height": 16,
						"originX": 0,
						"originY": 0,
						"originalSource": "",
						"exportFormat": "lossless",
						"exportQuality": 0.8,
						"fileType": "image/png",
						"imageSpriteId": 5453137,
						"useCollisionPoly": true,
						"duration": 1,
						"tag": ""
					},
					{
						"width": 16,
						"height": 16,
						"originX": 0,
						"originY": 0,
						"originalSource": "",
						"exportFormat": "lossless",
						"exportQuality": 0.8,
						"fileType": "image/png",
						"imageSpriteId": 5124113,
						"useCollisionPoly": true,
						"duration": 1,
						"tag": ""
					},
					{
						"width": 16,
						"height": 16,
						"originX": 0,
						"originY": 0,
						"originalSource": "",
						"exportFormat": "lossless",
						"exportQuality": 0.8,
						"fileType": "image/png",
						"imageSpriteId": 1288244,
						"useCollisionPoly": true,
						"duration": 1,
						"tag": ""
					}
				],
				"sid": 477181553606428,
				"name": "Bottom",
				"isLooping": true,
				"isPingPong": false,
				"repeatCount": 1,
				"repeatTo": 0,
				"speed": 8
			}
		],
		"subfolders": []
	}
}